README.rst
setup.py
apkutils/__init__.py
apkutils/__main__.py
apkutils/apkfile.py
apkutils/cert.py
apkutils/manifest.py
apkutils/axml/__init__.py
apkutils/axml/arscparser.py
apkutils/axml/axmlparser.py
apkutils/axml/chunk.py
apkutils/axml/public.py
apkutils/dex/__init__.py
apkutils/dex/byteio.py
apkutils/dex/dalvik.py
apkutils/dex/dalvikformats.py
apkutils/dex/dexparser.py
apkutils/dex/flags.py
apkutils/dex/mutf8.py
apkutils/dex/treelist.py
apkutils/dex/util.py
apkutils/elf/__init__.py
apkutils/elf/elfparser.py
apkutils/gui/__init__.py
apkutils/gui/__main__.py
apkutils_patch.egg-info/PKG-INFO
apkutils_patch.egg-info/SOURCES.txt
apkutils_patch.egg-info/dependency_links.txt
apkutils_patch.egg-info/requires.txt
apkutils_patch.egg-info/top_level.txt